{"football1": {"10": [{"HOME": [], "AWAY": [{"name": "Alessandro Tosi", "shortName": "A. Tosi", "time": "10'", "id": "56545", "type": "FootballYellowCard", "position": 2}]}], "15": [{"HOME": [], "AWAY": [{"name": "Matteo Valli Casadei", "shortName": "M. Valli Casadei", "time": "15'", "id": "88852", "type": "FootballYellowCard", "position": 3}]}], "17": [{"AWAY": [], "HOME": [{"name": "Tjay De Barr", "shortName": "T. De Barr", "time": "17'", "id": "1275", "type": "FootballYellowCard", "position": 4}]}], "23": [{"AWAY": [], "HOME": [{"name": "Ethan Britto", "shortName": "E. Britto", "time": "23'", "id": "970", "type": "FootballYellowCard", "position": 4}]}]}, "football2": {"60": [{"HOME": [], "AWAY": [{"name": "Samuele Zannoni", "shortName": "S. Zannoni", "time": "60'", "id": "94568", "type": "FootballYellowCard", "position": 3}]}]}, "summary": [], "status": "62'"}