{"football1": {"36": [{"HOME": [{"name": "David Vukovic", "shortName": "D. Vukovic", "time": "36'", "id": "89051", "type": "FootballYellowCard", "position": 3}], "AWAY": [{"name": "Francois Andre Dulysse", "shortName": "F. Dulysse", "time": "36'", "id": "41495", "type": "FootballYellowCard", "position": 2}]}], "37": [{"HOME": [], "AWAY": [{"name": "Albano Aleksi", "shortName": "A. Aleksi", "time": "37'", "id": "36941", "type": "FootballYellowCard", "position": 3}]}]}, "football2": {"49": [{"HOME": [], "AWAY": [{"name": "Abdurraman Fangaj", "shortName": "A. Fangaj", "time": "49'", "id": "89003", "type": "FootballYellowCard", "position": 3}]}], "58": [{"HOME": [], "AWAY": [{"name": "Arbin Zejnulai", "shortName": "A. Zejnulai", "time": "58'", "id": "58500", "type": "FootballRedCard", "position": 3}]}], "63": [{"HOME": [], "AWAY": [{"name": "Edison Ndreca", "shortName": "E. Ndreca", "time": "63'", "id": "89002", "type": "FootballYellowCard", "position": 3}, {"name": "Zamiq Aliyev", "shortName": "Z. Aliyev", "time": "63'", "id": "71030", "type": "FootballYellowCard", "position": 2}]}], "90+6": [{"HOME": [{"name": "Damir Hrelja", "shortName": "D. Hrelja", "time": "90 + 6'", "id": "89048", "score": {"home": "1", "away": "0"}, "type": "FootballGoal", "assist": [{"name": "Sebastián Herera", "shortName": "S. Herera"}]}], "AWAY": []}], "90+11": [{"HOME": [], "AWAY": [{"name": "Edison Ndreca", "shortName": "E. Ndreca", "time": "90 + 11'", "id": "89002", "type": "FootballRedYellowCard", "position": 3}]}], "90+15": [{"HOME": [], "AWAY": [{"name": "Arbenit Xhemajli", "shortName": "A. Xhemajli", "time": "90 + 15'", "id": "30812", "type": "FootballYellowCard", "position": 2}]}]}, "summary": ["The match was end! Borac Banja Luka won!", "Score fulltime: 1 - 0"], "status": "FT"}