{"football2": {"57": [{"HOME": [{"name": "Alejandro Pozo", "shortName": "A. Pozo", "time": "57'", "id": "19195", "playerId": "19195", "playerNameSlug": "alejandro-pozo", "score": {"home": "1", "away": "0"}, "type": "FootballGoal", "assist": [{"name": "Léo Baptistão", "shortName": "L. Baptistão", "id": "5705"}]}], "AWAY": []}], "59": [{"HOME": [], "AWAY": [{"name": "Jose Calderon", "shortName": "J. Calderon", "time": "59'", "id": "18427", "playerId": "18427", "playerNameSlug": "jose-calderon", "type": "FootballYellowCard", "position": 2}]}]}, "summary": ["The match was end! Cordoba won!", "Score fulltime: 2 - 0"], "status": "62'"}