{"football1": {"11": [{"HOME": [{"name": "Juan Tomas Ortuno Martinez", "shortName": "J. Ortuno Martinez", "time": "11'", "id": "70391", "playerId": "70391", "playerNameSlug": "juan-tomas-ortuno-martinez", "score": {"home": "1", "away": "0"}, "type": "FootballGoal", "assist": [{"name": "Víctor Garcia Raja", "shortName": "V. Garcia Raja", "id": "50642"}]}], "AWAY": []}], "34": [{"AWAY": [{"name": "Samed Bazdar", "shortName": "S. Bazdar", "time": "34'", "id": "35620", "playerId": "35620", "playerNameSlug": "samed-bazdar", "score": {"home": "1", "away": "1"}, "type": "FootballGoal", "assist": [{"name": "Keidi Bare", "shortName": "K. Bare", "id": "18341"}]}], "HOME": []}], "45+3": [{"AWAY": [], "HOME": [{"name": "Víctor Garcia Raja", "shortName": "V. Garcia Raja", "time": "45 + 3'", "id": "50642", "playerId": "50642", "playerNameSlug": "victor-garcia-raja", "type": "FootballYellowCard", "position": 2}]}], "45+4": [{"AWAY": [{"name": "Ivan Azon Monzon", "shortName": "I. Azon Monzon", "time": "45 + 4'", "id": "18389", "playerId": "18389", "playerNameSlug": "ivan-azon-monzon", "score": {"home": "1", "away": "2"}, "type": "FootballGoal", "assist": [{"name": "Ager Aketxe", "shortName": "A. Aketxe", "id": "18952"}]}], "HOME": []}]}, "football2": {"66": [{"HOME": [], "AWAY": [{"name": "Keidi Bare", "shortName": "K. Bare", "time": "66'", "id": "18341", "playerId": "18341", "playerNameSlug": "keidi-bare", "type": "FootballYellowCard", "position": 3}]}], "72": [{"HOME": [{"name": "Youness Lachhab", "shortName": "Y. Lachhab", "time": "72'", "id": "71709", "playerId": "71709", "playerNameSlug": "youness-lachhab", "score": {"home": "2", "away": "2"}, "type": "FootballGoal", "position": 3}], "AWAY": []}]}, "summary": ["The match ended in a draw!", "Score fulltime: 2 - 2"], "status": "73'"}