{"football1": {"16": [{"HOME": [], "AWAY": [{"name": "Vangelis Pavlidis", "shortName": "V. Pavlidis", "time": "16'", "id": "19985", "playerId": "19985", "playerNameSlug": "vangelis-pavlidis", "type": "FootballYellowCard", "position": 4}]}], "45+2": [{"AWAY": [], "HOME": [{"name": "Jose Gomes", "shortName": "J. Gomes", "time": "45 + 2'", "id": "575065", "type": "FootballYellowCard"}]}], "45+3": [{"HOME": [], "AWAY": [{"name": "Alexander Bah", "shortName": "A. Bah", "time": "45 + 3'", "id": "8472", "playerId": "8472", "playerNameSlug": "alexander-bah", "type": "FootballYellowCard", "position": 2}]}]}, "football2": {"59": [{"AWAY": [{"name": "Ángel Di María", "shortName": "Á. Di María", "time": "59'", "id": "2122", "playerId": "2122", "playerNameSlug": "angel-di-maria", "score": {"home": "0", "away": "1"}, "type": "FootballGoalPen", "position": 3}], "HOME": []}], "62": [{"HOME": [], "AWAY": [{"name": "Ángel Di María", "shortName": "Á. Di María", "time": "62'", "id": "2122", "playerId": "2122", "playerNameSlug": "angel-di-maria", "type": "FootballYellowCard", "position": 3}]}], "67": [{"AWAY": [], "HOME": [{"name": "Djibril Soumare", "shortName": "D. Soumare", "time": "67'", "id": "1518436", "type": "FootballYellowCard"}]}], "74": [{"AWAY": [{"name": "Ángel Di María", "shortName": "Á. Di María", "time": "74'", "id": "2122", "playerId": "2122", "playerNameSlug": "angel-di-maria", "score": {"home": "0", "away": "2"}, "type": "FootballGoal", "assist": [{"name": "Zeki Amdouni", "shortName": "Z. Amdouni", "id": "12466"}]}], "HOME": []}], "84": [{"HOME": [], "AWAY": [{"name": "Leandro Martins", "shortName": "L. Martins", "time": "84'", "id": "14509", "playerId": "14509", "playerNameSlug": "leandro-martins", "type": "FootballYellowCard", "position": 5}]}]}, "summary": [], "status": "90+2'"}