{"football1": {"23": [{"AWAY": [{"name": "Timothy Ouma", "shortName": "T. Ouma", "time": "23'", "id": "56115", "score": {"home": "0", "away": "1"}, "type": "FootballGoal", "assist": [{"name": "Simon Hedlund", "shortName": "S. Hedlund"}]}], "HOME": []}], "44": [{"HOME": [{"name": "Ruben van Bommel", "shortName": "R. van Bommel", "time": "44'", "id": "20814", "score": {"home": "1", "away": "1"}, "type": "FootballGoal", "position": 3}], "AWAY": []}]}, "football2": {"50": [{"HOME": [{"name": "Ruben van Bommel", "shortName": "R. van Bommel", "time": "50'", "id": "20814", "score": {"home": "2", "away": "1"}, "type": "FootballGoal", "position": 3}], "AWAY": []}]}, "summary": [], "status": "50'"}