{"football1": {"21": [{"AWAY": [], "HOME": [{"name": "Allan", "shortName": "Allan", "time": "21'", "id": "5856", "playerId": "5856", "playerNameSlug": "allan", "type": "FootballYellowCard", "position": 3}]}], "36": [{"HOME": [], "AWAY": [{"name": "Fausto Vera", "shortName": "F. Vera", "time": "36'", "id": "24809", "playerId": "24809", "playerNameSlug": "fausto-vera", "type": "FootballYellowCard", "position": 3}]}], "45": [{"HOME": [], "AWAY": [{"name": "Everson", "shortName": "Everson", "time": "45'", "id": "5859", "playerId": "5859", "playerNameSlug": "everson", "type": "FootballYellowCard", "position": 1}]}]}, "football2": {"48": [{"HOME": [], "AWAY": [{"name": "Renzo Saravia", "shortName": "R. Saravia", "time": "48'", "id": "5414", "playerId": "5414", "playerNameSlug": "renzo-saravia", "type": "FootballYellowCard", "position": 2}]}], "53": [{"HOME": [], "AWAY": [{"name": "Hulk", "shortName": "Hulk", "time": "53'", "id": "5843", "playerId": "5843", "playerNameSlug": "hulk", "type": "FootballYellowCard", "position": 4}]}]}, "summary": [], "status": "56'"}