{"homeStarters": [{"id": "37906", "playerId": "37906", "playerNameSlug": "devis-vasquez", "name": "Devis Vásquez", "shortName": "D. Vásquez", "number": 23, "fieldPosition": "1:1", "minOut": "", "position": "GOALKEEPER", "positionId": 1}, {"id": "75593", "playerId": "75593", "playerNameSlug": "saba-goglichidze", "name": "Saba Goglichidze", "shortName": "S. Goglichidze", "number": 2, "fieldPosition": "2:1", "minOut": "", "position": "DEFENDER", "positionId": 2, "card": "FootballRedCard"}, {"id": "16274", "playerId": "16274", "playerNameSlug": "ardian-ismajli", "name": "Ardian Ismajli", "shortName": "A. Ismajli", "number": 34, "fieldPosition": "2:2", "minOut": "", "position": "DEFENDER", "positionId": 2}, {"id": "16279", "playerId": "16279", "playerNameSlug": "mattia-viti", "name": "Mattia Viti", "shortName": "M. Viti", "number": 21, "fieldPosition": "2:3", "minOut": "", "position": "DEFENDER", "positionId": 2}, {"id": "17151", "playerId": "17151", "playerNameSlug": "emmanuel-gyasi", "name": "Emmanuel Gyasi", "shortName": "E. Gyasi", "number": 11, "fieldPosition": "3:1", "minOut": "", "position": "MIDFIELDER", "positionId": 3, "sub": {"id": "17151", "playerId": "17151", "playerNameSlug": "emmanuel-gyasi", "subPlayerId": "2067", "subType": "FootballSubOut", "subTime": "77'", "name": "Emmanuel Gyasi", "shortName": "E. Gyasi", "team": "HOME"}}, {"id": "37564", "playerId": "37564", "playerNameSlug": "tino-anjorin", "name": "Tino Anjorin", "shortName": "T. Anjorin", "number": 8, "fieldPosition": "3:2", "minOut": "", "position": "MIDFIELDER", "positionId": 3, "sub": {"id": "37564", "playerId": "37564", "playerNameSlug": "tino-anjorin", "subPlayerId": "15673", "subType": "FootballSubOut", "subTime": "57'", "name": "Tino Anjorin", "shortName": "T. Anjorin", "team": "HOME"}}, {"id": "15920", "playerId": "15920", "playerNameSlug": "youssef-maleh", "name": "Youssef Maleh", "shortName": "Y. Maleh", "number": 93, "fieldPosition": "3:3", "minOut": "", "position": "MIDFIELDER", "positionId": 3, "sub": {"id": "15920", "playerId": "15920", "playerNameSlug": "youssef-maleh", "subPlayerId": "16265", "subType": "FootballSubOut", "subTime": "57'", "name": "Youssef Maleh", "shortName": "Y. Maleh", "team": "HOME"}}, {"id": "16276", "playerId": "16276", "playerNameSlug": "liberato-cacace", "name": "Liberato Cacace", "shortName": "L. Cacace", "number": 13, "fieldPosition": "3:4", "minOut": "", "position": "MIDFIELDER", "positionId": 3, "card": "FootballYellowCard"}, {"id": "39806", "playerId": "39806", "playerNameSlug": "ola-solbakken", "name": "Ola Solbakken", "shortName": "O. Solbakken", "number": 17, "fieldPosition": "4:1", "minOut": "", "position": "MIDFIELDER", "positionId": 3, "sub": {"id": "39806", "playerId": "39806", "playerNameSlug": "ola-solbakken", "subPlayerId": "15696", "subType": "FootballSubOut", "subTime": "46'", "name": "Ola Solbakken", "shortName": "O. Solbakken", "team": "HOME"}}, {"id": "9518", "playerId": "9518", "playerNameSlug": "jacopo-fazzini", "name": "Jacopo Fazzini", "shortName": "J. Fazzini", "number": 10, "fieldPosition": "4:2", "minOut": "", "position": "MIDFIELDER", "positionId": 3}, {"id": "317", "playerId": "317", "playerNameSlug": "lorenzo-colombo", "name": "Lorenzo Colombo", "shortName": "L. Colombo", "number": 29, "fieldPosition": "5:1", "minOut": "", "position": "FORWARD", "positionId": 4, "sub": {"id": "317", "playerId": "317", "playerNameSlug": "lorenzo-colombo", "subPlayerId": "15989", "subType": "FootballSubOut", "subTime": "66'", "name": "Lorenzo Colombo", "shortName": "L. Colombo", "team": "HOME"}}], "awayStarters": [{"id": "13818", "playerId": "13818", "playerNameSlug": "yann-sommer", "name": "Yann Sommer", "shortName": "Y. Sommer", "number": 1, "fieldPosition": "1:1", "minOut": "", "position": "GOALKEEPER", "positionId": 1}, {"id": "1217", "playerId": "1217", "playerNameSlug": "yann-bisseck", "name": "Yann Bisseck", "shortName": "Y. Bisseck", "number": 31, "fieldPosition": "2:1", "minOut": "", "position": "DEFENDER", "positionId": 2}, {"id": "16012", "playerId": "16012", "playerNameSlug": "stefan-de-vrij", "name": "Stefan de Vrij", "shortName": "S. de Vrij", "number": 6, "fieldPosition": "2:2", "minOut": "", "position": "DEFENDER", "positionId": 2, "sub": {"id": "16012", "playerId": "16012", "playerNameSlug": "stefan-de-vrij", "subPlayerId": "24660", "subType": "FootballSubOut", "subTime": "81'", "name": "Stefan de Vrij", "shortName": "S. de Vrij", "team": "AWAY"}}, {"id": "16026", "playerId": "16026", "playerNameSlug": "alessandro-bastoni", "name": "Alessandro Bastoni", "shortName": "A. Bastoni", "number": 95, "fieldPosition": "2:3", "minOut": "", "position": "DEFENDER", "positionId": 2, "card": "FootballYellowCard", "sub": {"id": "16026", "playerId": "16026", "playerNameSlug": "alessandro-bastoni", "subPlayerId": "15385", "subType": "FootballSubOut", "subTime": "65'", "name": "Alessandro Bastoni", "shortName": "A. Bastoni", "team": "AWAY"}}, {"id": "16006", "playerId": "16006", "playerNameSlug": "matteo-darmian", "name": "Matteo Darmian", "shortName": "M. Darmian", "number": 36, "fieldPosition": "3:1", "minOut": "", "position": "MIDFIELDER", "positionId": 3}, {"id": "18091", "playerId": "18091", "playerNameSlug": "davide-frattesi", "name": "Davide Frattesi", "shortName": "D. Frattesi", "number": 16, "fieldPosition": "3:2", "minOut": "", "position": "MIDFIELDER", "positionId": 3, "goal": {"type": "FootballGoal", "amt": 2}}, {"id": "16021", "playerId": "16021", "playerNameSlug": "nicolo-barella", "name": "Nicolò Barella", "shortName": "N. Barella", "number": 23, "fieldPosition": "3:3", "minOut": "", "position": "MIDFIELDER", "positionId": 3}, {"id": "16192", "playerId": "16192", "playerNameSlug": "henrikh-mkhitaryan", "name": "Henrikh Mkhitaryan", "shortName": "H. Mkhitaryan", "number": 22, "fieldPosition": "3:4", "minOut": "", "position": "MIDFIELDER", "positionId": 3, "sub": {"id": "16192", "playerId": "16192", "playerNameSlug": "henrikh-mkhitaryan", "subPlayerId": "16571", "subType": "FootballSubOut", "subTime": "65'", "name": "Henrikh Mkhitaryan", "shortName": "H. Mkhitaryan", "team": "AWAY"}}, {"id": "16019", "playerId": "16019", "playerNameSlug": "federico-dimarco", "name": "Federico Dimarco", "shortName": "F. Dimarco", "number": 32, "fieldPosition": "3:5", "minOut": "", "position": "MIDFIELDER", "positionId": 3, "sub": {"id": "16019", "playerId": "16019", "playerNameSlug": "federico-dimarco", "subPlayerId": "16023", "subType": "FootballSubOut", "subTime": "65'", "name": "Federico Dimarco", "shortName": "F. Dimarco", "team": "AWAY"}}, {"id": "16025", "playerId": "16025", "playerNameSlug": "lautaro-martinez", "name": "Lautaro Martínez", "shortName": "L. Martínez", "number": 10, "fieldPosition": "4:1", "minOut": "", "position": "FORWARD", "positionId": 4, "goal": {"type": "FootballGoal", "amt": 1}}, {"id": "13831", "playerId": "13831", "playerNameSlug": "marcus-thuram", "name": "Marcus Thuram", "shortName": "M. Thuram", "number": 9, "fieldPosition": "4:2", "minOut": "", "position": "FORWARD", "positionId": 4, "sub": {"id": "13831", "playerId": "13831", "playerNameSlug": "marcus-thuram", "subPlayerId": "21243", "subType": "FootballSubOut", "subTime": "75'", "name": "Marcus Thuram", "shortName": "M. Thuram", "team": "AWAY"}}], "homeSubs": [{"id": "57845", "playerId": "57845", "playerNameSlug": "jacopo-seghetti", "name": "Jacopo Seghetti", "shortName": "J. Seghetti", "number": 12, "minOut": "", "position": "SUBSTITUTE_PLAYER", "positionId": 5}, {"id": "9297", "playerId": "9297", "playerNameSlug": "federico-brancolini", "name": "Federico Brancolini", "shortName": "F. Brancolini", "number": 98, "minOut": "", "position": "SUBSTITUTE_PLAYER", "positionId": 5}, {"id": "15673", "playerId": "15673", "playerNameSlug": "giuseppe-pezzella", "name": "Giuseppe Pezzella", "shortName": "G. Pezzella", "number": 3, "minOut": "", "position": "SUBSTITUTE_PLAYER", "positionId": 5, "sub": {"id": "15673", "playerId": "15673", "playerNameSlug": "giuseppe-pezzella", "subPlayerId": "37564", "subType": "FootballSubIn", "subTime": "57'", "name": "Giuseppe Pezzella", "shortName": "G. Pezzella", "team": "HOME"}}, {"id": "15696", "playerId": "15696", "playerNameSlug": "mattia-de-sciglio", "name": "Mattia De Sciglio", "shortName": "M. De Sciglio", "number": 22, "minOut": "", "position": "SUBSTITUTE_PLAYER", "positionId": 5, "sub": {"id": "15696", "playerId": "15696", "playerNameSlug": "mattia-de-sciglio", "subPlayerId": "39806", "subType": "FootballSubIn", "subTime": "46'", "name": "Mattia De Sciglio", "shortName": "M. De Sciglio", "team": "HOME"}}, {"id": "92730", "playerId": "92730", "playerNameSlug": "lorenzo-tosto", "name": "Lorenzo Tosto", "shortName": "L. Tosto", "number": 31, "minOut": "", "position": "SUBSTITUTE_PLAYER", "positionId": 5}, {"id": "74214", "playerId": "74214", "playerNameSlug": "luca-marianucci", "name": "Luca Marianucci", "shortName": "L. Marianucci", "number": 35, "minOut": "", "position": "SUBSTITUTE_PLAYER", "positionId": 5}, {"id": "16735", "playerId": "16735", "playerNameSlug": "alberto-grassi", "name": "Alberto Grassi", "shortName": "A. Grassi", "number": 5, "minOut": "", "position": "SUBSTITUTE_PLAYER", "positionId": 5}, {"id": "16265", "playerId": "16265", "playerNameSlug": "liam-henderson", "name": "Liam Henderson", "shortName": "L. Henderson", "number": 6, "minOut": "", "position": "SUBSTITUTE_PLAYER", "positionId": 5, "sub": {"id": "16265", "playerId": "16265", "playerNameSlug": "liam-henderson", "subPlayerId": "15920", "subType": "FootballSubIn", "subTime": "57'", "name": "Liam Henderson", "shortName": "L. Henderson", "team": "HOME"}}, {"id": "2067", "playerId": "2067", "playerNameSlug": "junior-sambia", "name": "Junior Sambia", "shortName": "J. Sambia", "number": 7, "minOut": "", "position": "SUBSTITUTE_PLAYER", "positionId": 5, "sub": {"id": "2067", "playerId": "2067", "playerNameSlug": "junior-sambia", "subPlayerId": "17151", "subType": "FootballSubIn", "subTime": "77'", "name": "Junior Sambia", "shortName": "J. Sambia", "team": "HOME"}}, {"id": "17747", "playerId": "17747", "playerNameSlug": "luca-belardinelli", "name": "Luca Belardinelli", "shortName": "L. Belardinelli", "number": 16, "minOut": "", "position": "SUBSTITUTE_PLAYER", "positionId": 5}, {"id": "16269", "playerId": "16269", "playerNameSlug": "nicolas-haas", "name": "Nicolas Haas", "shortName": "N. Haas", "number": 32, "minOut": "", "position": "SUBSTITUTE_PLAYER", "positionId": 5}, {"id": "15989", "playerId": "15989", "playerNameSlug": "pietro-pellegri", "name": "Pietro Pellegri", "shortName": "P. Pellegri", "number": 9, "minOut": "", "position": "SUBSTITUTE_PLAYER", "positionId": 5, "sub": {"id": "15989", "playerId": "15989", "playerNameSlug": "pietro-pellegri", "subPlayerId": "317", "subType": "FootballSubIn", "subTime": "66'", "name": "Pietro Pellegri", "shortName": "P. Pellegri", "team": "HOME"}}, {"id": "16282", "playerId": "16282", "playerNameSlug": "emmanuel-ekong", "name": "Emmanuel Ekong", "shortName": "E. Ekong", "number": 19, "minOut": "", "position": "SUBSTITUTE_PLAYER", "positionId": 5}, {"id": "94723", "playerId": "94723", "playerNameSlug": "ismael-konate", "name": "Ismael Konate", "shortName": "I. Konate", "number": 90, "minOut": "", "position": "SUBSTITUTE_PLAYER", "positionId": 5}], "awaySubs": [{"id": "16958", "playerId": "16958", "playerNameSlug": "raffaele-di-gennaro", "name": "Raffaele Di Gennaro", "shortName": "R. Di Gennaro", "number": 12, "minOut": "", "position": "SUBSTITUTE_PLAYER", "positionId": 5}, {"id": "28463", "playerId": "28463", "playerNameSlug": "josep-martinez", "name": "Josep Martínez", "shortName": "J. Martínez", "number": 13, "minOut": "", "position": "SUBSTITUTE_PLAYER", "positionId": 5}, {"id": "16023", "playerId": "16023", "playerNameSlug": "denzel-dumfries", "name": "Denzel Dumfries", "shortName": "D. Dumfries", "number": 2, "minOut": "", "position": "SUBSTITUTE_PLAYER", "positionId": 5, "sub": {"id": "16023", "playerId": "16023", "playerNameSlug": "denzel-dumfries", "subPlayerId": "16019", "subType": "FootballSubIn", "subTime": "65'", "name": "Denzel Dumfries", "shortName": "D. Dumfries", "team": "AWAY"}}, {"id": "15385", "playerId": "15385", "playerNameSlug": "benjamin-pavard", "name": "Benjamin Pavard", "shortName": "B. Pavard", "number": 28, "minOut": "", "position": "SUBSTITUTE_PLAYER", "positionId": 5, "sub": {"id": "15385", "playerId": "15385", "playerNameSlug": "benjamin-pavard", "subPlayerId": "16026", "subType": "FootballSubIn", "subTime": "65'", "name": "Benjamin Pavard", "shortName": "B. Pavard", "team": "AWAY"}}, {"id": "24660", "playerId": "24660", "playerNameSlug": "tiago-palacios", "name": "Tiago Palacios", "shortName": "T. Palacios", "number": 42, "minOut": "", "position": "SUBSTITUTE_PLAYER", "positionId": 5, "sub": {"id": "24660", "playerId": "24660", "playerNameSlug": "tiago-palacios", "subPlayerId": "16012", "subType": "FootballSubIn", "subTime": "81'", "name": "Tiago Palacios", "shortName": "T. Palacios", "team": "AWAY"}}, {"id": "16571", "playerId": "16571", "playerNameSlug": "piotr-zielinski", "name": "Piotr Zieliński", "shortName": "P. Zieliński", "number": 7, "minOut": "", "position": "SUBSTITUTE_PLAYER", "positionId": 5, "sub": {"id": "16571", "playerId": "16571", "playerNameSlug": "piotr-zielinski", "subPlayerId": "16192", "subType": "FootballSubIn", "subTime": "65'", "name": "Piotr Zieliński", "shortName": "P. Zieliński", "team": "AWAY"}}, {"id": "19342", "playerId": "19342", "playerNameSlug": "tajon-buchanan", "name": "Tajon Buchanan", "shortName": "T. Buchanan", "number": 17, "minOut": "", "position": "SUBSTITUTE_PLAYER", "positionId": 5}, {"id": "16280", "playerId": "16280", "playerNameSlug": "kristjan-asllani", "name": "Kristjan Asllani", "shortName": "K. Asllani", "number": 21, "minOut": "", "position": "SUBSTITUTE_PLAYER", "positionId": 5}, {"id": "96433", "playerId": "96433", "playerNameSlug": "thomas-berenbruch", "name": "Thomas Berenbruch", "shortName": "T. Berenbruch", "number": 52, "minOut": "", "position": "SUBSTITUTE_PLAYER", "positionId": 5}, {"id": "15616", "playerId": "15616", "playerNameSlug": "marko-arnautovic", "name": "Marko Arnautović", "shortName": "M. Arnautović", "number": 8, "minOut": "", "position": "SUBSTITUTE_PLAYER", "positionId": 5}, {"id": "16018", "playerId": "16018", "playerNameSlug": "joaquin-correa", "name": "Joaquin Correa", "shortName": "J. Correa", "number": 11, "minOut": "", "position": "SUBSTITUTE_PLAYER", "positionId": 5}, {"id": "21243", "playerId": "21243", "playerNameSlug": "mehdi-taremi", "name": "Mehdi Taremi", "shortName": "M. Taremi", "number": 99, "minOut": "", "position": "SUBSTITUTE_PLAYER", "positionId": 5, "sub": {"id": "21243", "playerId": "21243", "playerNameSlug": "mehdi-taremi", "subPlayerId": "13831", "subType": "FootballSubIn", "subTime": "75'", "name": "Mehdi Taremi", "shortName": "M. Taremi", "team": "AWAY"}}], "homeCoach": [{"id": "70886", "playerId": "70886", "playerNameSlug": "roberto-daversa", "name": "Roberto D'Aversa", "shortName": "R. D'Aversa", "minOut": "", "position": "COACH", "positionId": 10}], "awayCoach": [{"id": "16001", "playerId": "16001", "playerNameSlug": "simone-inzaghi", "name": "Simone Inzaghi", "shortName": "S. Inzaghi", "minOut": "", "position": "COACH", "positionId": 10}]}