{"homeStarters": [{"id": "30423", "playerId": "30423", "playerNameSlug": "matt-freese", "name": "Matt Freese", "shortName": "M. Freese", "number": 25, "fieldPosition": "1:1", "minOut": "", "position": "GOALKEEPER", "positionId": 1, "card": "FootballYellowCard"}, {"id": "35966", "playerId": "35966", "playerNameSlug": "alex-freeman", "name": "Alex Freeman", "shortName": "A. Freeman", "number": 16, "fieldPosition": "2:1", "minOut": "", "position": "DEFENDER", "positionId": 2}, {"id": "14742", "playerId": "14742", "playerNameSlug": "chris-richards", "name": "Chris Richards", "shortName": "C. Richards", "number": 3, "fieldPosition": "2:2", "minOut": "", "position": "DEFENDER", "positionId": 2, "card": "FootballYellowCard"}, {"id": "31177", "playerId": "31177", "playerNameSlug": "tim-ream", "name": "Tim Ream", "shortName": "T. Ream", "number": 13, "fieldPosition": "2:3", "minOut": "", "position": "DEFENDER", "positionId": 2}, {"id": "62994", "playerId": "62994", "playerNameSlug": "max-arfsten", "name": "Max Arfsten", "shortName": "M. Arfsten", "number": 18, "fieldPosition": "2:4", "minOut": "85'", "position": "DEFENDER", "positionId": 2, "sub": {"id": "62994", "playerId": "62994", "playerNameSlug": "max-arfsten", "name": "Max Arfsten", "shortName": "M. Arfsten", "subPlayerId": "32471", "subTime": "85'", "subType": "FootballSubOut", "time": 85, "team": "HOME"}}, {"id": "28461", "playerId": "28461", "playerNameSlug": "tyler-adams", "name": "Tyler Adams", "shortName": "T. Adams", "number": 4, "fieldPosition": "3:1", "minOut": "77'", "position": "MIDFIELDER", "positionId": 3, "sub": {"id": "28461", "playerId": "28461", "playerNameSlug": "tyler-adams", "name": "Tyler Adams", "shortName": "T. Adams", "subPlayerId": "30429", "subTime": "77'", "subType": "FootballSubOut", "time": 77, "team": "HOME"}}, {"id": "20826", "playerId": "20826", "playerNameSlug": "luca-de-la-torre", "name": "Luca de la Torre", "shortName": "L. d. la Torre", "number": 14, "fieldPosition": "3:2", "minOut": "58'", "position": "MIDFIELDER", "positionId": 3, "card": "FootballYellowCard", "sub": {"id": "20826", "playerId": "20826", "playerNameSlug": "luca-de-la-torre", "name": "Luca de la Torre", "shortName": "L. d. la Torre", "subPlayerId": "6480", "subTime": "58'", "subType": "FootballSubOut", "time": 58, "team": "HOME"}}, {"id": "8039", "playerId": "8039", "playerNameSlug": "sebastian-berhalter", "name": "Sebastian Berhalter", "shortName": "S. Berhalter", "number": 8, "fieldPosition": "4:1", "minOut": "", "position": "MIDFIELDER", "positionId": 3}, {"id": "15393", "playerId": "15393", "playerNameSlug": "malik-tillman", "name": "Malik Tillman", "shortName": "M. Tillman", "number": 17, "fieldPosition": "4:2", "minOut": "", "position": "MIDFIELDER", "positionId": 3}, {"id": "47046", "playerId": "47046", "playerNameSlug": "diego-luna", "name": "Diego Luna", "shortName": "D. Luna", "number": 10, "fieldPosition": "4:3", "minOut": "77'", "position": "MIDFIELDER", "positionId": 3, "card": "FootballYellowCard", "goal": {"type": "FootballGoal", "amt": 2}, "sub": {"id": "47046", "playerId": "47046", "playerNameSlug": "diego-luna", "name": "Diego Luna", "shortName": "D. Luna", "subPlayerId": "13418", "subTime": "77'", "subType": "FootballSubOut", "time": 77, "team": "HOME"}}, {"id": "63911", "playerId": "63911", "playerNameSlug": "patrick-agyemang", "name": "Patrick Agyemang", "shortName": "P. Agyemang", "number": 24, "fieldPosition": "5:1", "minOut": "85'", "position": "FORWARD", "positionId": 4, "sub": {"id": "63911", "playerId": "63911", "playerNameSlug": "patrick-agyemang", "name": "Patrick Agyemang", "shortName": "P. Agyemang", "subPlayerId": "63449", "subTime": "85'", "subType": "FootballSubOut", "time": 85, "team": "HOME"}}], "awayStarters": [{"id": "35724", "playerId": "35724", "playerNameSlug": "alessandro-navarro", "name": "Alessandro Navarro", "shortName": "A. Navarro", "number": 12, "fieldPosition": "1:1", "minOut": "", "position": "GOALKEEPER", "positionId": 1}, {"id": "35376", "playerId": "35376", "playerNameSlug": "aaron-herrera", "name": "Aaron Herrera", "shortName": "A. Herrera", "number": 7, "fieldPosition": "2:1", "minOut": "", "position": "DEFENDER", "positionId": 2}, {"id": "70091", "playerId": "70091", "playerNameSlug": "jose-pinto", "name": "Jose Pinto", "shortName": "J. Pinto", "number": 4, "fieldPosition": "2:2", "minOut": "", "position": "DEFENDER", "positionId": 2}, {"id": "70092", "playerId": "70092", "playerNameSlug": "nicolas-samayoa", "name": "Nicolas Samayoa", "shortName": "N. Samayoa", "number": 3, "fieldPosition": "2:3", "minOut": "", "position": "DEFENDER", "positionId": 2}, {"id": "35710", "playerId": "35710", "playerNameSlug": "jose-morales", "name": "Jose Morales", "shortName": "J. Morales", "number": 16, "fieldPosition": "2:4", "minOut": "", "position": "DEFENDER", "positionId": 2}, {"id": "35718", "playerId": "35718", "playerNameSlug": "oscar-santis", "name": "Oscar Santis", "shortName": "O. Santis", "number": 18, "fieldPosition": "3:1", "minOut": "", "position": "MIDFIELDER", "positionId": 3, "card": "FootballYellowCard"}, {"id": "35721", "playerId": "35721", "playerNameSlug": "stheven-robles", "name": "Stheven Robles", "shortName": "S. Robles", "number": 13, "fieldPosition": "3:2", "minOut": "65'", "position": "MIDFIELDER", "positionId": 3, "card": "FootballYellowCard", "sub": {"id": "35721", "playerId": "35721", "playerNameSlug": "stheven-robles", "name": "Stheven Robles", "shortName": "S. Robles", "subPlayerId": "67067", "subTime": "65'", "subType": "FootballSubOut", "time": 65, "team": "AWAY"}}, {"id": "105033", "playerId": "105033", "playerNameSlug": "jose-rosales", "name": "Jose Rosales", "shortName": "J. Rosales", "number": 5, "fieldPosition": "3:3", "minOut": "65'", "position": "MIDFIELDER", "positionId": 3, "sub": {"id": "105033", "playerId": "105033", "playerNameSlug": "jose-rosales", "name": "Jose Rosales", "shortName": "J. Rosales", "subPlayerId": "35720", "subTime": "65'", "subType": "FootballSubOut", "time": 65, "team": "AWAY"}}, {"id": "67081", "playerId": "67081", "playerNameSlug": "rudy-munoz", "name": "Rudy Munoz", "shortName": "R. Munoz", "number": 11, "fieldPosition": "3:4", "minOut": "65'", "position": "MIDFIELDER", "positionId": 3, "sub": {"id": "67081", "playerId": "67081", "playerNameSlug": "rudy-munoz", "name": "Rudy Munoz", "shortName": "R. Munoz", "subPlayerId": "79988", "subTime": "65'", "subType": "FootballSubOut", "time": 65, "team": "AWAY"}}, {"id": "35366", "playerId": "35366", "playerNameSlug": "rubio-rubin", "name": "Rubio Rubin", "shortName": "R. Rubin", "number": 9, "fieldPosition": "4:1", "minOut": "70'", "position": "FORWARD", "positionId": 4, "sub": {"id": "35366", "playerId": "35366", "playerNameSlug": "rubio-rubin", "name": "Rubio Rubin", "shortName": "R. Rubin", "subPlayerId": "35722", "subTime": "70'", "subType": "FootballSubOut", "time": 70, "team": "AWAY"}}, {"id": "70093", "playerId": "70093", "playerNameSlug": "pedro-altan", "name": "Pedro Altan", "shortName": "P. Altan", "number": 10, "fieldPosition": "4:2", "minOut": "70'", "position": "FORWARD", "positionId": 4, "sub": {"id": "70093", "playerId": "70093", "playerNameSlug": "pedro-altan", "name": "Pedro Altan", "shortName": "P. Altan", "subPlayerId": "67080", "subTime": "70'", "subType": "FootballSubOut", "time": 70, "team": "AWAY"}}], "homeSubs": [{"id": "13536", "playerId": "13536", "playerNameSlug": "matt-turner", "name": "Matt Turner", "shortName": "M. Turner", "number": 1, "minOut": "", "position": "SUBSTITUTE_PLAYER", "positionId": 5}, {"id": "6480", "playerId": "6480", "playerNameSlug": "brenden-aaronson", "name": "Brenden Aaronson", "shortName": "B. Aaronson", "number": 11, "minOut": "58'", "position": "SUBSTITUTE_PLAYER", "positionId": 5, "sub": {"id": "6480", "playerId": "6480", "playerNameSlug": "brenden-aaronson", "name": "Brenden Aaronson", "shortName": "B. Aaronson", "subPlayerId": "20826", "subTime": "58'", "subType": "FootballSubIn", "time": 58, "team": "HOME"}}, {"id": "30426", "playerId": "30426", "playerNameSlug": "paxten-aaronson", "name": "Paxten Aaronson", "shortName": "P. Aaronson", "number": 21, "minOut": "", "position": "SUBSTITUTE_PLAYER", "positionId": 5}, {"id": "63449", "playerId": "63449", "playerNameSlug": "damion-downs", "name": "Damion Downs", "shortName": "D. Downs", "number": 9, "minOut": "85'", "position": "SUBSTITUTE_PLAYER", "positionId": 5, "sub": {"id": "63449", "playerId": "63449", "playerNameSlug": "damion-downs", "name": "Damion Downs", "shortName": "D. Downs", "subPlayerId": "63911", "subTime": "85'", "subType": "FootballSubIn", "time": 85, "team": "HOME"}}, {"id": "30424", "playerId": "30424", "playerNameSlug": "nathan-harriel", "name": "Nathan Harriel", "shortName": "N. Harriel", "number": 20, "minOut": "", "position": "SUBSTITUTE_PLAYER", "positionId": 5}, {"id": "30427", "playerId": "30427", "playerNameSlug": "quinn-sullivan", "name": "Quinn Sullivan", "shortName": "Q. Sullivan", "number": 7, "minOut": "", "position": "SUBSTITUTE_PLAYER", "positionId": 5}, {"id": "30429", "playerId": "30429", "playerNameSlug": "jack-mcglynn", "name": "Jack McGlynn", "shortName": "J. McGlynn", "number": 6, "minOut": "77'", "position": "SUBSTITUTE_PLAYER", "positionId": 5, "sub": {"id": "30429", "playerId": "30429", "playerNameSlug": "jack-mcglynn", "name": "Jack McGlynn", "shortName": "J. McGlynn", "subPlayerId": "28461", "subTime": "77'", "subType": "FootballSubIn", "time": 77, "team": "HOME"}}, {"id": "19425", "playerId": "19425", "playerNameSlug": "mark-mckenzie", "name": "Mark McKenzie", "shortName": "M. McKenzie", "number": 22, "minOut": "", "position": "SUBSTITUTE_PLAYER", "positionId": 5}, {"id": "22275", "playerId": "22275", "playerNameSlug": "miles-robinson", "name": "Miles Robinson", "shortName": "M. Robinson", "number": 12, "minOut": "", "position": "SUBSTITUTE_PLAYER", "positionId": 5}, {"id": "13418", "playerId": "13418", "playerNameSlug": "john-tolkin", "name": "John Tolkin", "shortName": "J. Tolkin", "number": 2, "minOut": "77'", "position": "SUBSTITUTE_PLAYER", "positionId": 5, "sub": {"id": "13418", "playerId": "13418", "playerNameSlug": "john-tolkin", "name": "John Tolkin", "shortName": "J. Tolkin", "subPlayerId": "47046", "subTime": "77'", "subType": "FootballSubIn", "time": 77, "team": "HOME"}}, {"id": "8031", "playerId": "8031", "playerNameSlug": "brian-white", "name": "Brian White", "shortName": "B. White", "number": 23, "minOut": "", "position": "SUBSTITUTE_PLAYER", "positionId": 5}, {"id": "32471", "playerId": "32471", "playerNameSlug": "walker-zimmerman", "name": "Walker Zimmerman", "shortName": "W. Zimmerman", "number": 5, "minOut": "85'", "position": "SUBSTITUTE_PLAYER", "positionId": 5, "sub": {"id": "32471", "playerId": "32471", "playerNameSlug": "walker-zimmerman", "name": "Walker Zimmerman", "shortName": "W. Zimmerman", "subPlayerId": "62994", "subTime": "85'", "subType": "FootballSubIn", "time": 85, "team": "HOME"}}], "awaySubs": [{"id": "105034", "playerId": "105034", "playerNameSlug": "luis-moran", "name": "Luis Moran", "shortName": "L. Moran", "number": 21, "minOut": "", "position": "SUBSTITUTE_PLAYER", "positionId": 5}, {"id": "105036", "playerId": "105036", "playerNameSlug": "carlos-aguilar", "name": "Carlos Aguilar", "shortName": "C. Aguilar", "number": 24, "minOut": "", "position": "SUBSTITUTE_PLAYER", "positionId": 5}, {"id": "66454", "playerId": "66454", "playerNameSlug": "jose-ardon", "name": "Jose Ardon", "shortName": "J. Ardon", "number": 2, "minOut": "", "position": "SUBSTITUTE_PLAYER", "positionId": 5}, {"id": "85585", "playerId": "85585", "playerNameSlug": "elmer-cardoza", "name": "Elmer Cardoza", "shortName": "E. Cardoza", "number": 23, "minOut": "", "position": "SUBSTITUTE_PLAYER", "positionId": 5}, {"id": "35720", "playerId": "35720", "playerNameSlug": "oscar-castellanos", "name": "Oscar Castellanos", "shortName": "O. Castellanos", "number": 17, "minOut": "65'", "position": "SUBSTITUTE_PLAYER", "positionId": 5, "sub": {"id": "35720", "playerId": "35720", "playerNameSlug": "oscar-castellanos", "name": "Oscar Castellanos", "shortName": "O. Castellanos", "subPlayerId": "105033", "subTime": "65'", "subType": "FootballSubIn", "time": 65, "team": "AWAY"}}, {"id": "79988", "playerId": "79988", "playerNameSlug": "olger-escobar", "name": "Olger Escobar", "shortName": "O. Escobar", "number": 20, "minOut": "65'", "position": "SUBSTITUTE_PLAYER", "positionId": 5, "goal": {"type": "FootballGoal", "amt": 1}, "sub": {"id": "79988", "playerId": "79988", "playerNameSlug": "olger-escobar", "name": "Olger Escobar", "shortName": "O. Escobar", "subPlayerId": "67081", "subTime": "65'", "subType": "FootballSubIn", "time": 65, "team": "AWAY"}}, {"id": "67067", "playerId": "67067", "playerNameSlug": "jonathan-franco", "name": "Jonathan Franco", "shortName": "J. Franco", "number": 22, "minOut": "65'", "position": "SUBSTITUTE_PLAYER", "positionId": 5, "sub": {"id": "67067", "playerId": "67067", "playerNameSlug": "jonathan-franco", "name": "Jonathan Franco", "shortName": "J. Franco", "subPlayerId": "35721", "subTime": "65'", "subType": "FootballSubIn", "time": 65, "team": "AWAY"}}, {"id": "35722", "playerId": "35722", "playerNameSlug": "darwin-lom", "name": "Darwin Lom", "shortName": "D. Lom", "number": 14, "minOut": "70'", "position": "SUBSTITUTE_PLAYER", "positionId": 5, "sub": {"id": "35722", "playerId": "35722", "playerNameSlug": "darwin-lom", "name": "Darwin Lom", "shortName": "D. Lom", "subPlayerId": "35366", "subTime": "70'", "subType": "FootballSubIn", "time": 70, "team": "AWAY"}}, {"id": "102232", "playerId": "102232", "playerNameSlug": "erick-lemus", "name": "Erick Lemus", "shortName": "E. Lemus", "number": 6, "minOut": "", "position": "SUBSTITUTE_PLAYER", "positionId": 5}, {"id": "67080", "playerId": "67080", "playerNameSlug": "arquimides-ordonez", "name": "Arquimides Ordonez", "shortName": "A. Ordonez", "number": 19, "minOut": "70'", "position": "SUBSTITUTE_PLAYER", "positionId": 5, "sub": {"id": "67080", "playerId": "67080", "playerNameSlug": "arquimides-ordonez", "name": "Arquimides Ordonez", "shortName": "A. Ordonez", "subPlayerId": "70093", "subTime": "70'", "subType": "FootballSubIn", "time": 70, "team": "AWAY"}}, {"id": "105035", "playerId": "105035", "playerNameSlug": "kevin-ramirez", "name": "Kevin Ramirez", "shortName": "K. Ramirez", "number": 25, "minOut": "", "position": "SUBSTITUTE_PLAYER", "positionId": 5}, {"id": "53470", "playerId": "53470", "playerNameSlug": "rodrigo-saravia", "name": "Rodrigo Saravia", "shortName": "R. Saravia", "number": 8, "minOut": "", "position": "SUBSTITUTE_PLAYER", "positionId": 5}], "homeCoach": [{"id": "2118", "playerId": "2118", "playerNameSlug": "mauricio-pochettino", "name": "Mauricio Pochettino", "shortName": "M. Pochettino", "minOut": "", "position": "COACH", "positionId": 10}], "awayCoach": [{"id": "35698", "playerId": "35698", "playerNameSlug": "luis-fernando-tena", "name": "Luis Fernando Tena", "shortName": "L. Tena", "minOut": "", "position": "COACH", "positionId": 10}]}