{"homeStarters": [{"id": "15005", "playerId": "15005", "playerNameSlug": "tim-schreiber", "name": "Tim Schreiber", "shortName": "T. Schreiber", "number": 1, "minOut": "", "position": "GOALKEEPER", "positionId": 1}, {"id": "14705", "playerId": "14705", "playerNameSlug": "konrad-faber", "name": "Konrad Faber", "shortName": "K. Faber", "number": 2, "minOut": "", "position": "DEFENDER", "positionId": 2}, {"id": "15136", "playerId": "15136", "playerNameSlug": "vinko-sapina", "name": "Vinko Sapina", "shortName": "V. Sapina", "number": 5, "minOut": "", "position": "MIDFIELDER", "positionId": 3}, {"id": "79836", "playerId": "79836", "playerNameSlug": "kofi-amoako", "name": "Kofi Amoako", "shortName": "K. Amoako", "number": 6, "minOut": "", "position": "MIDFIELDER", "positionId": 3}, {"id": "60903", "playerId": "60903", "playerNameSlug": "jakob-lemmer", "name": "Jakob Lemmer", "shortName": "J. Lemmer", "number": 10, "minOut": "", "position": "FORWARD", "positionId": 4}, {"id": "15578", "playerId": "15578", "playerNameSlug": "dominik-kother", "name": "Dominik Kother", "shortName": "D. Kother", "number": 11, "minOut": "", "position": "MIDFIELDER", "positionId": 3}, {"id": "13945", "playerId": "13945", "playerNameSlug": "nils-froling", "name": "Nils Froling", "shortName": "N. Froling", "number": 16, "minOut": "", "position": "FORWARD", "positionId": 4}, {"id": "37431", "playerId": "37431", "playerNameSlug": "lars-bunning", "name": "Lars Bunning", "shortName": "L. Bunning", "number": 23, "minOut": "", "position": "DEFENDER", "positionId": 2}, {"id": "15350", "playerId": "15350", "playerNameSlug": "niklas-hauptmann", "name": "Niklas Hauptmann", "shortName": "N. Hauptmann", "number": 27, "minOut": "64'", "position": "MIDFIELDER", "positionId": 3, "sub": {"id": "15350", "playerId": "15350", "playerNameSlug": "niklas-hauptmann", "name": "Niklas Hauptmann", "shortName": "N. Hauptmann", "subPlayerId": "15179", "subTime": "64'", "subType": "FootballSubOut", "time": 64, "team": "HOME"}}, {"id": "37524", "playerId": "37524", "playerNameSlug": "sascha-risch", "name": "Sascha Risch", "shortName": "S. Risch", "number": 28, "minOut": "", "position": "DEFENDER", "positionId": 2}, {"id": "14442", "playerId": "14442", "playerNameSlug": "lukas-boeder", "name": "Lukas Boeder", "shortName": "L. Boeder", "number": 29, "minOut": "", "position": "DEFENDER", "positionId": 2}], "awayStarters": [{"id": "14500", "playerId": "14500", "playerNameSlug": "robin-zentner", "name": "Robin Zentner", "shortName": "R. Zentner", "number": 27, "minOut": "", "position": "GOALKEEPER", "positionId": 1}, {"id": "60758", "playerId": "60758", "playerNameSlug": "kaishu-sano", "name": "Kaishu Sano", "shortName": "K. Sano", "number": 6, "minOut": "", "position": "MIDFIELDER", "positionId": 3}, {"id": "14514", "playerId": "14514", "playerNameSlug": "paul-nebel", "name": "Paul Nebel", "shortName": "P. Nebel", "number": 8, "minOut": "", "position": "MIDFIELDER", "positionId": 3}, {"id": "2951", "playerId": "2951", "playerNameSlug": "arnaud-nordin", "name": "Arnaud Nordin", "shortName": "A. Nordin", "number": 9, "minOut": "", "position": "FORWARD", "positionId": 4}, {"id": "16542", "playerId": "16542", "playerNameSlug": "nadiem-amiri", "name": "Nadiem Amiri", "shortName": "N. Amiri", "number": 10, "minOut": "", "position": "MIDFIELDER", "positionId": 3, "goal": {"type": "FootballGoal", "amt": 1}}, {"id": "15396", "playerId": "15396", "playerNameSlug": "armindo-sieb", "name": "Armindo Sieb", "shortName": "A. Sieb", "number": 11, "minOut": "", "position": "FORWARD", "positionId": 4}, {"id": "14494", "playerId": "14494", "playerNameSlug": "stefan-bell", "name": "Stefan Bell", "shortName": "S. Bell", "number": 16, "minOut": "46'", "position": "DEFENDER", "positionId": 2, "sub": {"id": "14494", "playerId": "14494", "playerNameSlug": "stefan-bell", "name": "Stefan Bell", "shortName": "S. Bell", "subPlayerId": "14194", "subTime": "46'", "subType": "FootballSubOut", "time": 46, "team": "AWAY"}}, {"id": "15210", "playerId": "15210", "playerNameSlug": "benedict-hollerbach", "name": "Benedict Hollerbach", "shortName": "B. Hollerbach", "number": 17, "minOut": "64'", "position": "FORWARD", "positionId": 4, "sub": {"id": "15210", "playerId": "15210", "playerNameSlug": "benedict-hollerbach", "name": "Benedict Hollerbach", "shortName": "B. Hollerbach", "subPlayerId": "14518", "subTime": "64'", "subType": "FootballSubOut", "time": 64, "team": "AWAY"}}, {"id": "15435", "playerId": "15435", "playerNameSlug": "danny-da-costa", "name": "Danny da Costa", "shortName": "D. da Costa", "number": 21, "minOut": "", "position": "DEFENDER", "positionId": 2}, {"id": "14498", "playerId": "14498", "playerNameSlug": "silvan-widmer", "name": "Silvan Widmer", "shortName": "S. Widmer", "number": 30, "minOut": "", "position": "DEFENDER", "positionId": 2}, {"id": "14497", "playerId": "14497", "playerNameSlug": "dominik-kohr", "name": "Dominik Kohr", "shortName": "D. Kohr", "number": 31, "minOut": "64'", "position": "MIDFIELDER", "positionId": 3, "sub": {"id": "14497", "playerId": "14497", "playerNameSlug": "dominik-kohr", "name": "Dominik Kohr", "shortName": "D. Kohr", "subPlayerId": "19615", "subTime": "64'", "subType": "FootballSubOut", "time": 64, "team": "AWAY"}}], "homeSubs": [{"id": "15601", "playerId": "15601", "playerNameSlug": "lennart-grill", "name": "Lennart Grill", "shortName": "L. Grill", "number": 22, "minOut": "", "position": "SUBSTITUTE_PLAYER", "positionId": 5}, {"id": "15179", "playerId": "15179", "playerNameSlug": "luca-herrmann", "name": "Luca Herrmann", "shortName": "L. Herrmann", "number": 8, "minOut": "64'", "position": "SUBSTITUTE_PLAYER", "positionId": 5, "sub": {"id": "15179", "playerId": "15179", "playerNameSlug": "luca-herrmann", "name": "Luca Herrmann", "shortName": "L. Herrmann", "subPlayerId": "15350", "subTime": "64'", "subType": "FootballSubIn", "time": 64, "team": "HOME"}}, {"id": "37521", "playerId": "37521", "playerNameSlug": "claudio-kammerknecht", "name": "Claudio Kammerknecht", "shortName": "C. Kammerknecht", "number": 15, "minOut": "", "position": "SUBSTITUTE_PLAYER", "positionId": 5}, {"id": "55800", "playerId": "55800", "playerNameSlug": "aljaz-casar", "name": "Aljaz Casar", "shortName": "A. Casar", "number": 17, "minOut": "", "position": "SUBSTITUTE_PLAYER", "positionId": 5}, {"id": "73078", "playerId": "73078", "playerNameSlug": "tony-menzel", "name": "Tony Menzel", "shortName": "T. Menzel", "number": 24, "minOut": "", "position": "SUBSTITUTE_PLAYER", "positionId": 5}, {"id": "52602", "playerId": "52602", "playerNameSlug": "jonas-oehmichen", "name": "Jonas Oehmichen", "shortName": "J. Oehmichen", "number": 25, "minOut": "", "position": "SUBSTITUTE_PLAYER", "positionId": 5}, {"id": "14533", "playerId": "14533", "playerNameSlug": "jan-hendrik-marx", "name": "Jan-Hendrik Marx", "shortName": "J. Marx", "number": 26, "minOut": "", "position": "SUBSTITUTE_PLAYER", "positionId": 5}, {"id": "37446", "playerId": "37446", "playerNameSlug": "stefan-kutschke", "name": "Stefan Kutschke", "shortName": "S. Kutschke", "number": 30, "minOut": "", "position": "SUBSTITUTE_PLAYER", "positionId": 5}, {"id": "36683", "playerId": "36683", "playerNameSlug": "david-kubatta", "name": "David Kubatta", "shortName": "D. Kubatta", "number": 39, "minOut": "", "position": "SUBSTITUTE_PLAYER", "positionId": 5}], "awaySubs": [{"id": "14516", "playerId": "14516", "playerNameSlug": "lasse-riess", "name": "Lasse Riess", "shortName": "L. Riess", "number": 1, "minOut": "", "position": "SUBSTITUTE_PLAYER", "positionId": 5}, {"id": "20040", "playerId": "20040", "playerNameSlug": "philipp-mwene", "name": "Philipp Mwene", "shortName": "P. Mwene", "number": 2, "minOut": "", "position": "SUBSTITUTE_PLAYER", "positionId": 5}, {"id": "14194", "playerId": "14194", "playerNameSlug": "maxim-leitsch", "name": "Maxim Leitsch", "shortName": "M. Leitsch", "number": 5, "minOut": "46'", "position": "SUBSTITUTE_PLAYER", "positionId": 5, "sub": {"id": "14194", "playerId": "14194", "playerNameSlug": "maxim-leitsch", "name": "Maxim Leitsch", "shortName": "M. Leitsch", "subPlayerId": "14494", "subTime": "46'", "subType": "FootballSubIn", "time": 46, "team": "AWAY"}}, {"id": "14503", "playerId": "14503", "playerNameSlug": "lee-jae-sung", "name": "Lee Jae-sung", "shortName": "L. Jae-sung", "number": 7, "minOut": "", "position": "SUBSTITUTE_PLAYER", "positionId": 5}, {"id": "13996", "playerId": "13996", "playerNameSlug": "lennard-maloney", "name": "Lennard Maloney", "shortName": "L. Maloney", "number": 15, "minOut": "", "position": "SUBSTITUTE_PLAYER", "positionId": 5}, {"id": "2607", "playerId": "2607", "playerNameSlug": "anthony-caci", "name": "Anthony Caci", "shortName": "A. Caci", "number": 19, "minOut": "", "position": "SUBSTITUTE_PLAYER", "positionId": 5}, {"id": "23720", "playerId": "23720", "playerNameSlug": "sota-kawasaki", "name": "Sota Kawasaki", "shortName": "S. Kawasaki", "number": 24, "minOut": "", "position": "SUBSTITUTE_PLAYER", "positionId": 5}, {"id": "19615", "playerId": "19615", "playerNameSlug": "andreas-hanche-olsen", "name": "Andreas Hanche-Olsen", "shortName": "A. Hanche-Olsen", "number": 25, "minOut": "64'", "position": "SUBSTITUTE_PLAYER", "positionId": 5, "sub": {"id": "19615", "playerId": "19615", "playerNameSlug": "andreas-hanche-olsen", "name": "Andreas Hanche-Olsen", "shortName": "A. Hanche-Olsen", "subPlayerId": "14497", "subTime": "64'", "subType": "FootballSubIn", "time": 64, "team": "AWAY"}}, {"id": "14518", "playerId": "14518", "playerNameSlug": "ben-bobzien", "name": "Ben Bobzien", "shortName": "B. Bobzien", "number": 37, "minOut": "64'", "position": "SUBSTITUTE_PLAYER", "positionId": 5, "sub": {"id": "14518", "playerId": "14518", "playerNameSlug": "ben-bobzien", "name": "Ben Bobzien", "shortName": "B. Bobzien", "subPlayerId": "15210", "subTime": "64'", "subType": "FootballSubIn", "time": 64, "team": "AWAY"}}], "homeCoach": [{"id": "8724", "name": "Thomas Stamm", "shortName": "T. Stamm", "minOut": "", "position": "COACH", "positionId": 10}], "awayCoach": [{"id": "1143", "playerId": "1143", "playerNameSlug": "bo-henriksen", "name": "Bo Henriksen", "shortName": "B. Henriksen", "minOut": "", "position": "COACH", "positionId": 10}]}