{"tCnt": 1, "ofst": 0, "lmt": 10, "arts": [{"id": "pr:2850-a:891247", "ttl": "Preview: PEC Zwolle vs. Fortuna Sittard - prediction, team news, lineups", "oTtl": "Sports Mole", "pId": 35, "sum": "Sports Mole previews Saturday's Eredivisie clash between PEC Zwolle and Fortuna Sittard, including predictions, team news and possible lineups.", "cnUrl": "https://www.sportsmole.co.uk/football/pec-zwolle/preview/preview-pec-zwolle-vs-sittard-prediction-team-news-lineups_557627.html?utm_source=livescore&utm_medium=referral&utm_campaign=foryou", "tnUrl": "https://sm.imgix.net/24/30/anselmo-garcia_1.jpg", "pbAt": 1731015791403}]}