{"tCnt": 2, "ofst": 0, "lmt": 10, "arts": [{"id": "pr:2834-a:1410405", "ttl": "AFC Wimbledon beat Grimsby to secure play-off spot", "oTtl": "Press Association", "pId": 32, "sum": ".", "cnUrl": "https://www.livescore.com/en/native/news/afc-wimbledon-beat-grimsby-to-secure-play-off-spot-2025050316055104851/", "tnUrl": "https://image.assets.pressassociation.io/v2/image/production/dc615d68a7db8d4f9489ef9f8e5565f7Y29udGVudHNlYXJjaGFwaSwxNzQ2Mzc0NDM1/2.79548670.jpg?rect=0,194,7148,4021&ext=.jpg", "aiGen": false, "pbAt": 1746288156000}, {"id": "pr:2834-a:1403911", "ttl": "‘At risk’ – Grimsby Town vs AFC Wimbledon prediction: The72", "oTtl": "The72 - All Leagues", "athr": "James Ray", "pId": 35, "sum": "The72's writers offer their Grimsby Town vs AFC Wimbledon prediction ahead of the League Two clash on Saturday. The post ‘At risk’ – Grimsby Town vs AFC Wimbledon prediction: The72 appeared first on The72 - Football League News.", "cnUrl": "https://the72.co.uk/2025/05/02/grimsby-town-vs-afc-wimbledon-prediction/?utm_source=livescore&utm_medium=referral&utm_campaign=foryou", "tnUrl": "https://cdn.the72.co.uk/wp-content/uploads/2022/10/2021-08-24T201227Z_1904261402_RC2VBP9PUR3P_RTRMADP_3_SOCCER-ENGLAND-LEE-CAX-REPORT.jpg", "aiGen": false, "pbAt": 1746170646403}]}