{"Eid": "1242980", "Pids": {"1": "4341124", "112": "SBTE_2_1020617389", "30": "8edffe9f-f4f4-4407-bf5e-3992ae2a973f", "6": "48855687", "8": "1242980"}, "Sids": {"1": "886900", "112": "SBTC3_79667", "12": "SBTC3_79667", "30": "9767ade7-c4d5-4039-a38a-e52d11b6ee80", "36": "3aa4mumjl6zyetg6o9hwd5hhx", "6": "79972", "8": "15836"}, "Media": {"112": [{"eventId": "FIFA+", "provider": "ABELSON", "type": "TV_CHANNEL", "allowedCountries": ["GB"]}]}, "T1": [{"Nm": "Senegal", "ID": "9315", "Img": "enet/6395.png", "NewsTag": "/team/senegal-2021020913320920836-1715/", "Abr": "SEN", "tbd": 0, "Gd": 1, "Pids": {"33": ["2wk1549tkz80oet8226euj7jp"], "1": ["6395"], "12": ["SBTP_1_3629"], "112": ["SBTP_2_1000000255"], "36": ["2wk1549tkz80oet8226euj7jp"], "6": ["4739"], "28": ["18244"], "8": ["9315"], "30": ["309b1925-1a12-487c-ba8b-dcdf9186d7fd"]}, "CoNm": "Senegal", "CoId": "SEN", "HasVideo": true, "TO": 15}], "T2": [{"Nm": "Mauritania", "ID": "9189", "Img": "enet/68374.png", "NewsTag": "/team/mauritania-2021020913320920836-1533/", "Abr": "MTN", "tbd": 0, "Gd": 1, "Pids": {"1": ["68374"], "12": ["SBTP_1_18737"], "112": ["SBTP_2_1000013205"], "36": ["5xbd7ywlhu1ggkjfmyl9o3x09"], "6": ["4779"], "8": ["9189"], "30": ["86004c65-cbb2-444b-8914-6b350e5f81e3"]}, "CoNm": "Mauritania", "CoId": "MRT", "HasVideo": true, "TO": 15}], "Eps": "NS", "Esid": 1, "Epr": 0, "Ecov": 0, "ErnInf": "10", "Et": 1, "Esd": 20251014190000, "Eact": 1, "EO": 882688039, "EOX": 882688039, "LuC": 0, "Ehid": 0, "Spid": 1, "Stg": {"Sid": "15836", "Snm": "CAF Qualification: Group B", "Scd": "caf-qualification-group-b", "badgeUrl": "2026-world-cup.png", "Cid": "510", "Cnm": "World Cup Qualification", "CnmT": "world-cup-qualification", "Csnm": "World Cup Qualification", "Ccd": "world-cup-qualification", "CompId": "259", "CompN": "World Cup Qualifiers: CAF", "CompD": "World Cup 2026", "CompUrlName": "world-cup-qualifiers-caf", "Scu": 0, "Chi": 0, "Shi": 0, "Ccdiso": "NON", "Sdn": "CAF Qualification: Group B", "Feed": {"Id": "cp:259", "Items": ["cp:259-a:1760378805247", "cp:259-a:1760368307355", "cp:259-a:1760303288151", "cp:259-a:1760125635322", "cp:259-a:1760119460010"]}}, "Pid": 8, "Eloff": 0, "T1img": "https://lsm-static-prod.livescore.com/medium/enet/6395.png", "T2img": "https://lsm-static-prod.livescore.com/medium/enet/68374.png", "livetv": {"radarurl": "https://widgets.api-score.com/api/sport/football/animation?id=23xmvkh8oe0oqg8&view=true", "liveurl": [{"source": "XoilacTV", "name": "Xoilac TOM", "link": "https://mv-c767f67a88.fast5cdn.net/e3ba29cd2cda20159edd719a12adb722/1760475062858/channel-12/index.m3u8", "headers": {"Referer": "https://xlz.plcdn.xyz/"}}, {"source": "XoilacTV", "name": "Xoilac HD TOM", "link": "https://mv-c767f67a88.fast5cdn.net/5c58da9d7b23e3aa2e64242177b231da/1760475063225/channel-12/index.m3u8", "headers": {"Referer": "https://xlz.plcdn.xyz/"}}], "linkwebxoilac": "https://rileygainescenter.org/truc-tiep/senegal-vs-mauritania-luc-0200-ngay-15-10-2025/"}}