{"Eid": "1478862", "Pids": {"1": "4756669", "112": "SBTE_2_1023165044", "32": "7949713", "6": "59006309", "8": "1478862"}, "Sids": {"1": "898461", "112": "SBTC3_42282", "32": "7949637", "6": "84527", "8": "20938"}, "Media": {"112": [{"eventId": "av:stream:20977755", "provider": "SPORTRADAR", "type": "LIVE_STREAMING", "allowedCountries": ["BG", "GB", "IE"]}]}, "Tr1": "1", "Tr2": "0", "Trh1": "1", "Trh2": "0", "Tr1OR": "1", "Tr2OR": "0", "T1": [{"Nm": "WSG Tirol", "ID": "6518", "Img": "enet/1583.png", "Abr": "WSG", "tbd": 0, "Gd": 1, "Pids": {"1": ["1583"], "12": ["SBTP_1_779889"], "112": ["SBTP_2_1002098425"], "36": ["7uh2y9tk3j8dk6zinfu38pygi"], "6": ["5405"], "8": ["6518"], "30": ["21ef4714-57cd-49a0-9211-7f1a523012fe"], "32": ["4739"]}, "CoNm": "Austria", "CoId": "AUT", "HasVideo": false, "TO": 6}], "T2": [{"Nm": "SCR Altach", "ID": "4625", "Img": "enet/10008.png", "Abr": "RAL", "tbd": 0, "Gd": 1, "Pids": {"1": ["10008"], "12": ["SBTP_1_3224"], "112": ["SBTP_2_1000072591"], "36": ["3lcvs7iiylixau81d0lruwsak"], "6": ["4856"], "8": ["4625"], "30": ["b12e2e5a-13f0-4d80-bed6-4951e341daeb"], "32": ["503"]}, "CoNm": "Austria", "CoId": "AUT", "HasVideo": false, "TO": 2}], "Venue": {"id": "1141", "Vnm": "Tivoli Stadion Neu", "Vneut": 0}, "Eps": "HT", "Esid": 10, "Epr": 1, "Ecov": 0, "ErnInf": "27", "Et": 1, "Esd": 20250422163000, "LuUT": 20250422163026, "Eact": 1, "EO": 270418799, "EOX": 270418799, "LuC": 1, "Ehid": 0, "Spid": 1, "Stg": {"Sid": "20938", "Snm": "Bundesliga: Relegation", "Scd": "bundesliga-relegation", "badgeUrl": "2023-austria-bundesliga.png", "firstColor": "d81e05", "Cid": "149", "Cnm": "Austria", "CnmT": "austria", "Csnm": "Austria", "Ccd": "austria", "Scu": 0, "Sds": "Bundesliga: Relegation", "Chi": 0, "Shi": 0, "Ccdiso": "AUT", "Sdn": "Bundesliga: Relegation"}, "Pid": 8, "Eloff": 0, "Incs-s": {"1": [{"Min": 35, "Nm": 1, "Sc": [1, 0], "Sor": 0, "Incs": [{"Min": 35, "Nm": 1, "PosA": 3, "Aid": "36864", "ID": "36864", "Fn": "Valentino", "Ln": "Muller", "Pnt": "valentino-muller", "Pnum": 0, "Pn": "Valentino Mueller", "PnumO": 0, "IT": 36, "Sc": [1, 0], "Sor": 0}, {"Min": 35, "Nm": 1, "PosA": 4, "Aid": "36878", "ID": "36878", "Fn": "Stefan", "Ln": "Skrbo", "Pnt": "stefan-skrbo", "Pnum": 0, "Pn": "Stefan Skrbo", "PnumO": 0, "IT": 63, "Sc": [1, 0], "Sor": 1}]}]}, "T1img": "https://lsm-static-prod.livescore.com/medium/enet/1583.png", "T2img": "https://lsm-static-prod.livescore.com/medium/enet/10008.png", "livetv": {"radarurl": "https://widgets.api-score.com/api/sport/football/animation?id=pxwrxlh5dypyryk&view=true", "liveurl": [{"source": "XoilacTV", "name": "Xoilac ALEX", "link": "https://mv-c767f67a88-lb.fast5cdn.net/2ec35d8f9354d5228610b40208a4f08d/1745385461148/channel-2/index.m3u8", "headers": {"Referer": "https://xlz.plcdn.xyz/"}}, {"source": "XoilacTV", "name": "Xoilac HD ALEX", "link": "https://mv-c767f67a88-lb.fast5cdn.net/c2d3bdd5bddb09dcdc01db29e2af6c35/1745385461383/channel-2/index.m3u8", "headers": {"Referer": "https://xlz.plcdn.xyz/"}}], "linkwebxoilac": "https://www.winefoodbeer.com/truc-tiep/wsg-tirol-vs-rheindorf-altach-luc-2330-ngay-22-04-2025"}}