{"Eid": "1686704", "Pids": {"1": "5036802", "112": "SBTE_2_1025466472", "36": "46cu0b94j12c6ffas4fykydqs", "6": "65100040", "8": "1686704"}, "Sids": {"1": "909116", "112": "SBTC3_212383", "33": "awcfd8kz99e15zjjo01ktq7mc", "36": "3n9mk5b2mxmq831wfmv6pu86i", "6": "189410", "8": "23587"}, "Tr1": "1", "Tr2": "1", "Trh1": "0", "Trh2": "0", "Tr1OR": "1", "Tr2OR": "1", "Trp1": "3", "Trp2": "4", "T1": [{"Nm": "Andrezieux", "ID": "3344", "Img": "enet/161698.png", "Abr": "AND", "tbd": 0, "Gd": 1, "Pids": {"1": ["161698"], "12": ["SBTP_1_61339"], "112": ["SBTP_2_1000181028"], "36": ["1rcmkoz0tocbb4pt8gs4vdf1d"], "6": ["32870"], "8": ["3344"]}, "CoNm": "France", "CoId": "FRA", "HasVideo": false, "TO": 10}], "T2": [{"Nm": "Hauts Lyonnais", "ID": "9405", "Img": "enet/687558.png", "Abr": "HAU", "tbd": 0, "Gd": 1, "Pids": {"33": ["1igxzs8z5868hmrs3d3xmf93t"], "1": ["687558"], "112": ["SBTP_2_1003670790"], "36": ["1igxzs8z5868hmrs3d3xmf93t"], "6": ["300324"], "8": ["9405"], "30": ["871e3826-4623-4bea-a459-386eddc5a5ec"]}, "CoNm": "France", "CoId": "FRA", "HasVideo": false, "TO": 10}], "Eps": "AP", "Esid": 13, "Epr": 2, "Ecov": 2, "ErnInf": "7", "Ewt": 2, "Et": 1, "Esd": 20251115160000, "Edf": 20251115181935, "Eact": 1, "EO": 269504556, "EOX": 269504556, "LuC": 0, "Ehid": 0, "Spid": 1, "Stg": {"Sid": "23587", "Snm": "Coupe de France", "Scd": "coupe-de-france", "badgeUrl": "2023-coupe-de-france.png", "firstColor": "445B65", "Cid": "177", "Cnm": "France", "CnmT": "france", "Csnm": "France", "Ccd": "france", "CompId": "426", "CompN": "Coupe de France", "CompD": "France", "CompUrlName": "coupe-de-france", "CompST": "France", "Scu": 1, "Chi": 0, "Shi": 0, "Ccdiso": "FRA", "Sdn": "Coupe de France", "Feed": {"Id": "cp:426", "Items": ["cp:426-a:2386910", "cp:426-a:1748120506168", "cp:426-a:1506603", "cp:426-a:1506231", "cp:426-a:509669"]}}, "Pid": 8, "Eloff": 0, "Incs-s": {"1": [{"Nm": 1, "Pnum": 0, "PnumO": 0, "IT": 36, "Sc": [1, 0], "Sor": 50}, {"Nm": 2, "Pnum": 0, "PnumO": 0, "IT": 36, "Sc": [1, 1], "Sor": 60}]}, "T1img": "https://lsm-static-prod.livescore.com/medium/enet/161698.png", "T2img": "https://lsm-static-prod.livescore.com/medium/enet/687558.png", "livetv": {"liveurl": [], "radarurl": "https://widgets.api-score.com/api/sport/football/animation?id=318q66hx2yneqo9&view=true", "linkwebxoilac": ""}}